gpugo/__init__.py
gpugo/gpu.py
gpugo/main.py
gpugo/mutil.py
gpugo-0.1.3.dist-info/LICENSE
gpugo-0.1.3.dist-info/METADATA
gpugo-0.1.3.dist-info/WHEEL
gpugo-0.1.3.dist-info/entry_points.txt
gpugo-0.1.3.dist-info/top_level.txt
gpugo-0.1.3.dist-info/RECORD
