Metadata-Version: 2.1
Name: gpugo
Version: 0.1.3
Summary: Show GPU information and deep learning tasks assignment
Home-page: https://github.com/wuchangsheng951/gpugo
Author: Huiming Sun
Author-email: sunhuiming55@gmail.com
License: UNKNOWN
Platform: UNKNOWN
Classifier: Programming Language :: Python :: 3
Classifier: License :: OSI Approved :: MIT License
Classifier: Operating System :: OS Independent
Requires-Dist: click
Requires-Dist: pandas
Requires-Dist: loguru
